LICENSE
README.md
setup.py
src/testgear_cli/__init__.py
src/testgear_cli/__main__.py
src/testgear_cli/apiclient.py
src/testgear_cli/args_parser.py
src/testgear_cli/configurator.py
src/testgear_cli/converter.py
src/testgear_cli/importer.py
src/testgear_cli/logger.py
src/testgear_cli/parser.py
src/testgear_cli/service.py
src/testgear_cli.egg-info/PKG-INFO
src/testgear_cli.egg-info/SOURCES.txt
src/testgear_cli.egg-info/dependency_links.txt
src/testgear_cli.egg-info/entry_points.txt
src/testgear_cli.egg-info/requires.txt
src/testgear_cli.egg-info/top_level.txt
src/testgear_cli/models/__init__.py
src/testgear_cli/models/config.py
src/testgear_cli/models/mode.py
src/testgear_cli/models/status.py
src/testgear_cli/models/testcase.py
src/testgear_cli/models/testrun.py