Metadata-Version: 2.1
Name: testgear-cli
Version: 0.1.3
Summary: This tool is the command line wrapper of Test Gear allowing you to upload the test results in real time to Test Gear
Home-page: https://pypi.org/project/testgear/
Author: Integration team
Author-email: integrations@test-gear.io
License: Apache-2.0
Classifier: Programming Language :: Python :: 3
Classifier: Programming Language :: Python :: 3.6
Classifier: Programming Language :: Python :: 3.7
Classifier: Programming Language :: Python :: 3.8
Classifier: Programming Language :: Python :: 3.9
License-File: LICENSE
